robertcommonio/__init__.py
robertcommonio/system/__init__.py
robertcommonio/system/io/__init__.py
robertcommonio/system/io/data_storage.py
robertcommonio/system/io/email.py
robertcommonio/system/io/file.py
robertcommonio/system/io/ftp.py
robertcommonio/system/io/ftps.py
robertcommonio/system/io/http.py
robertcommonio/system/io/ini.py
robertcommonio/system/io/job.py
robertcommonio/system/io/license.py
robertcommonio/system/io/mongo.py
robertcommonio/system/io/mqtt.py
robertcommonio/system/io/mysql.py
robertcommonio/system/io/oss.py
robertcommonio/system/io/rabitmq.py
robertcommonio/system/io/redis.py
robertcommonio/system/io/redis_cache.py
robertcommonio/system/io/response.py
robertcommonio/system/io/socket.py
robertcommonio/system/io/sqlalche.py
robertcommonio/system/io/transport.py
robertcommonio/system/io/version.py
tests/__init__.py
tests/test_system/__init__.py
tests/test_system/test_io/__init__.py
tests/test_system/test_io/test.py
tests/test_system/test_io/test_data_storage.py
tests/test_system/test_io/test_email.py
tests/test_system/test_io/test_file.py
tests/test_system/test_io/test_ftp.py
tests/test_system/test_io/test_ftps.py
tests/test_system/test_io/test_http.py
tests/test_system/test_io/test_ini.py
tests/test_system/test_io/test_job.py
tests/test_system/test_io/test_license.py
tests/test_system/test_io/test_mongo.py
tests/test_system/test_io/test_mqtt.py
tests/test_system/test_io/test_oracle.py
tests/test_system/test_io/test_rabbitmq.py
tests/test_system/test_io/test_socket.py
tests/test_system/test_io/test_sqlalche.py
tests/test_system/test_io/test_transport.py
robertcommonio-0.1.66.dist-info/LICENSE
robertcommonio-0.1.66.dist-info/METADATA
robertcommonio-0.1.66.dist-info/WHEEL
robertcommonio-0.1.66.dist-info/top_level.txt
robertcommonio-0.1.66.dist-info/RECORD
