Metadata-Version: 2.1
Name: robertcommonio
Version: 0.1.66
Summary: Robert Common IO Library
Home-page: https://github.com/hun0423/RobertCommonIO
Author: Robert0423
Author-email: 851010070@qq.com
License: MIT
Platform: UNKNOWN
Classifier: License :: OSI Approved :: MIT License
Classifier: Programming Language :: Python
Classifier: Programming Language :: Python :: 3
Classifier: Programming Language :: Python :: 3.6
Classifier: Programming Language :: Python :: Implementation :: CPython
Classifier: Programming Language :: Python :: Implementation :: PyPy
Requires-Python: >=3.6.0
License-File: LICENSE
Requires-Dist: APScheduler
Requires-Dist: cryptography
Requires-Dist: DBUtils
Requires-Dist: Flask
Requires-Dist: MarkupSafe
Requires-Dist: numpy
Requires-Dist: openpyxl
Requires-Dist: oss2
Requires-Dist: paho-mqtt (==1.6.1)
Requires-Dist: pandas
Requires-Dist: pika
Requires-Dist: psutil
Requires-Dist: pycryptodome
Requires-Dist: pycryptodomex
Requires-Dist: pyftpdlib
Requires-Dist: pymongo
Requires-Dist: pymysql
Requires-Dist: pyserial
Requires-Dist: python-dateutil
Requires-Dist: pytz
Requires-Dist: pyzipper
Requires-Dist: redis
Requires-Dist: requests
Requires-Dist: RobertCommonBasic (>=0.1.51)
Requires-Dist: SQLAlchemy (==1.4.22)
Requires-Dist: XlsxWriter
